philharmonic/__init__.py
philharmonic/__main__.py
philharmonic/add_cluster_functions.py
philharmonic/build_cluster_graph.py
philharmonic/build_go_map.py
philharmonic/cluster_network.py
philharmonic/conduct.py
philharmonic/generate_candidates.py
philharmonic/summarize_clusters.py
philharmonic/utils.py
philharmonic-0.8.1.dist-info/LICENSE
philharmonic-0.8.1.dist-info/METADATA
philharmonic-0.8.1.dist-info/WHEEL
philharmonic-0.8.1.dist-info/entry_points.txt
philharmonic-0.8.1.dist-info/RECORD
