Metadata-Version: 2.1
Name: philharmonic
Version: 0.8.1
Summary: Decoding functional organization in non-model organisms
License: MIT
Author: Samuel Sledzieski
Author-email: samsl@mit.edu
Requires-Python: >=3.10,<4.0
Classifier: License :: OSI Approved :: MIT License
Classifier: Programming Language :: Python :: 3
Classifier: Programming Language :: Python :: 3.10
Classifier: Programming Language :: Python :: 3.11
Classifier: Programming Language :: Python :: 3.12
Classifier: Programming Language :: Python :: 3.13
Requires-Dist: biopython (>=1.84,<2.0)
Requires-Dist: dscript (>=0.2.8,<0.3.0)
Requires-Dist: fastdsd (>=1.0.1,<2.0.0)
Requires-Dist: hmmer (>=3.4.0.0,<4.0.0.0)
Requires-Dist: huggingface-hub (>=0.26.1,<0.27.0)
Requires-Dist: llm (>=0.16,<0.17)
Requires-Dist: loguru (>=0.7.2,<0.8.0)
Requires-Dist: matplotlib (>=3.9.2,<4.0.0)
Requires-Dist: networkx (>=3.4.2,<4.0.0)
Requires-Dist: numpy (>=1.26.4,<2.0.0) ; python_version >= "3.8" and python_version < "3.11"
Requires-Dist: numpy (>=2.1.2,<3.0.0) ; python_version >= "3.11"
Requires-Dist: pandas (>=2.2.3,<3.0.0)
Requires-Dist: pulp (==2.7.0) ; python_version >= "3.8" and python_version < "3.11"
Requires-Dist: pulp (>=2.9.0,<3.0.0) ; python_version >= "3.11"
Requires-Dist: recipe-cluster (>=0.0.4,<0.0.5)
Requires-Dist: regex (>=2024.9.11,<2025.0.0)
Requires-Dist: scikit-learn (>=1.5.2,<2.0.0)
Requires-Dist: scipy (==1.13.1) ; python_version >= "3.8" and python_version < "3.11"
Requires-Dist: scipy (>=1.14.1,<2.0.0) ; python_version >= "3.11"
Requires-Dist: seaborn (>=0.13.2,<0.14.0)
Requires-Dist: snakemake (>=7.0,<8.0) ; python_version >= "3.8" and python_version < "3.11"
Requires-Dist: snakemake (>=8.24.0,<9.0.0) ; python_version >= "3.11"
Requires-Dist: tqdm (>=4.66.5,<5.0.0)
Requires-Dist: transformers (>=4.45.2,<5.0.0)
Requires-Dist: typer (>=0.12.5,<0.13.0)
